optiview/__init__.py
optiview/app.py
optiview/app_manager.py
optiview/config.py
optiview/gst_graph.py
optiview/manifest_parser.py
optiview/mediasrc.py
optiview/process_manager.py
optiview/remote_devkit.py
optiview/remotefs.py
optiview/utils.py
optiview/watcher.py
optiview/bin/mediamtx
optiview/bin/mediamtx.yml
optiview/bin/vf
optiview/bin/static/drawing.js
optiview/bin/static/pagination.css
optiview/bin/static/pagination.js
optiview/bin/static/reverse.html
optiview/bin/static/settings.js
optiview/bin/static/viewer.css
optiview/bin/static/viewer.html
optiview/bin/static/viewer.js
optiview/bin/static/css/app-buttons.css
optiview/bin/static/css/roi.css
optiview/bin/static/css/settings.css
optiview/bin/static/icons/delete.png
optiview/bin/static/icons/menu.png
optiview/bin/static/js/roi.js
optiview/static/css/app-button.css
optiview/static/css/assign-src.css
optiview/static/css/editor.css
optiview/static/css/gst-editor.css
optiview/static/css/info.css
optiview/static/css/mediasrc.css
optiview/static/css/settings-popup.css
optiview/static/css/style.css
optiview/static/css/toast.css
optiview/static/css/upload.css
optiview/static/icons/assign.png
optiview/static/icons/brightmode.png
optiview/static/icons/coding.png
optiview/static/icons/darkmode.png
optiview/static/icons/delete.png
optiview/static/icons/fav.png
optiview/static/icons/folder.png
optiview/static/icons/gst_edit.png
optiview/static/icons/info.png
optiview/static/icons/logo.svg
optiview/static/icons/menu.png
optiview/static/icons/minimize.png
optiview/static/icons/number_1.png
optiview/static/icons/number_2.png
optiview/static/icons/number_3.png
optiview/static/icons/number_4.png
optiview/static/icons/number_5.png
optiview/static/icons/number_6.png
optiview/static/icons/number_7.png
optiview/static/icons/number_8.png
optiview/static/icons/number_9.png
optiview/static/icons/redo.png
optiview/static/icons/rocket.png
optiview/static/icons/save.png
optiview/static/icons/start-streaming.png
optiview-0.0.13.dist-info/METADATA
optiview-0.0.13.dist-info/WHEEL
optiview-0.0.13.dist-info/entry_points.txt
optiview-0.0.13.dist-info/top_level.txt
optiview-0.0.13.dist-info/RECORD
