Metadata-Version: 2.4
Name: optiview
Version: 0.0.13
Summary: Sima.ai Vision ML Development Tool
Author: Sima.ai
Author-email: support@sima.ai
License: MIT
Classifier: Programming Language :: Python :: 3
Classifier: Framework :: Flask
Classifier: Operating System :: OS Independent
Requires-Python: >=3.8
Requires-Dist: flask
Requires-Dist: watchdog
Requires-Dist: pillow
Requires-Dist: pymediainfo
Requires-Dist: psutil
Requires-Dist: pygobject
Requires-Dist: cryptography
Requires-Dist: paramiko
Requires-Dist: scp
Dynamic: author
Dynamic: author-email
Dynamic: classifier
Dynamic: license
Dynamic: requires-dist
Dynamic: requires-python
Dynamic: summary
